encache/__init__.py
encache-0.1.2.dist-info/licenses/LICENSE
encache-0.1.2.dist-info/METADATA
encache-0.1.2.dist-info/WHEEL
encache-0.1.2.dist-info/top_level.txt
encache-0.1.2.dist-info/RECORD
