Metadata-Version: 2.4
Name: encache
Version: 0.1.2
Summary: A small and easy caching system for every use
Home-page: https://github.com/EmanuelNorsk/encache
Author: Emanuel Odén Hesselroth
Author-email: Emanuel Odén Hesselroth <emanuelodenhesselroth@gmail.com>
License: MIT
Classifier: Programming Language :: Python :: 3
Classifier: License :: OSI Approved :: MIT License
Classifier: Operating System :: OS Independent
Requires-Python: >=3.6
License-File: LICENSE
Dynamic: author
Dynamic: home-page
Dynamic: license-file
